ximu3.cpython-311-i386-linux-gnu.so
ximu3-stubs/__init__.pyi
ximu3.libs/libblkid-d6efe991.so.1.1.0
ximu3.libs/libmount-4966c276.so.1.1.0
ximu3.libs/libpcre2-8-813ed30b.so.0.7.1
ximu3.libs/libselinux-4ff55052.so.1
ximu3.libs/libudev-b45e1ad2.so.1.6.11
ximu3.libs/libuuid-afcb1fdc.so.1.3.0
ximu3-1.7.2.dist-info/METADATA
ximu3-1.7.2.dist-info/WHEEL
ximu3-1.7.2.dist-info/top_level.txt
ximu3-1.7.2.dist-info/RECORD
ximu3-1.7.2.dist-info/licenses/LICENSE.md
