Metadata-Version: 2.4
Name: ximu3
Version: 1.7.2
Summary: x-IMU3 API
Author-email: x-io Technologies Limited <info@x-io.co.uk>
License: 
Project-URL: Repository, https://github.com/xioTechnologies/x-IMU3-Software
Classifier: Programming Language :: Python :: 3.8
Classifier: Programming Language :: Python :: 3.9
Classifier: Programming Language :: Python :: 3.10
Classifier: Programming Language :: Python :: 3.11
Classifier: Programming Language :: Python :: 3.12
Classifier: Programming Language :: Python :: 3.13
Classifier: Programming Language :: Python :: 3.14
License-File: LICENSE.md
Dynamic: license-file
